<?xml version = '1.0' encoding = 'UTF-8'?>
<Relation class="oracle.dbtools.crest.model.design.logical.Relation" name="sdvsddf" directorySegmentName="seg_0" id="B461B9BD-EF1B-47E4-1A3A-51C9EB4272A2">
<createdBy>sgorski</createdBy>
<createdTime>2017-03-24 08:27:48 UTC</createdTime>
<ownerDesignName>backup</ownerDesignName>
<engineerTo>
<item key="3BD31116-9726-45D8-4389-EF0DD5A82CF7" value="true"/>
</engineerTo>
<sourcePk>6977E8D3-764B-A014-CC3F-986AC04900C1</sourcePk>
<identifying>false</identifying>
<nameOnSource>wystawił</nameOnSource>
<nameOnTarget>została wystawiona przez</nameOnTarget>
<optionalSource>true</optionalSource>
<optionalTarget>false</optionalTarget>
<sourceCardinality>1</sourceCardinality>
<sourceEntity>B7213D2F-A3FF-99D4-16C3-A5908D7383B4</sourceEntity>
<targetCardinalityString>*</targetCardinalityString>
<targetEntity>232F15C6-E019-2691-7FA1-FD1E43231FE8</targetEntity>
<transferable>true</transferable>
<deleteRule>NO ACTION</deleteRule>
</Relation>